{
  "state": "LA",
  "data": {
    "2026-03-13": {
      "regular": 3.265,
      "midGrade": 3.707,
      "premium": 4.078,
      "diesel": 4.577
    },
    "2026-03-12": {
      "regular": 3.232,
      "midGrade": 3.688,
      "premium": 4.052,
      "diesel": 4.55
    },
    "2026-03-06": {
      "regular": 2.959,
      "midGrade": 3.408,
      "premium": 3.78,
      "diesel": 3.978
    },
    "2026-02-13": {
      "regular": 2.513,
      "midGrade": 2.95,
      "premium": 3.354,
      "diesel": 3.221
    },
    "2025-03-13": {
      "regular": 2.721,
      "midGrade": 3.162,
      "premium": 3.538,
      "diesel": 3.28
    },
    "2026-03-14": {
      "regular": 3.324,
      "midGrade": 3.747,
      "premium": 4.129,
      "diesel": 4.626
    },
    "2026-03-15": {
      "regular": 3.365,
      "midGrade": 3.791,
      "premium": 4.179,
      "diesel": 4.665
    },
    "2026-03-16": {
      "regular": 3.388,
      "midGrade": 3.816,
      "premium": 4.201,
      "diesel": 4.688
    },
    "2026-03-17": {
      "regular": 3.445,
      "midGrade": 3.883,
      "premium": 4.28,
      "diesel": 4.735
    },
    "2026-03-18": {
      "regular": 3.486,
      "midGrade": 3.912,
      "premium": 4.308,
      "diesel": 4.758
    },
    "2026-03-19": {
      "regular": 3.524,
      "midGrade": 3.951,
      "premium": 4.337,
      "diesel": 4.789
    }
  },
  "metadata": {
    "lastUpdated": "2026-03-19T14:45:26.495Z",
    "totalDays": 338,
    "firstDate": "2020-03-16",
    "lastDate": "2026-03-19"
  }
}